LICENSE
MANIFEST.in
NOTICE.md
README.md
pytest.ini
requirements-docs.txt
requirements-test.txt
requirements.txt
setup.py
tox.ini
steenzout/__init__.py
steenzout.object.egg-info/PKG-INFO
steenzout.object.egg-info/SOURCES.txt
steenzout.object.egg-info/dependency_links.txt
steenzout.object.egg-info/namespace_packages.txt
steenzout.object.egg-info/top_level.txt
steenzout/object/__init__.py
steenzout/object/metadata.py
tests/__init__.py
tests/object_test.py
tests/package_test.py
tests/singleton_test.py